fltk/__init__.py
fltk/_fltk.cp313-win_amd64.pyd
fltk/fltk.py
fltk/fltk_wrap.cpp
fltk/fltk_wrap.h
fltk/test/DragAndDrop.py
fltk/test/DraggableBox.py
fltk/test/GlobalHandler.py
fltk/test/HelpDialog.html
fltk/test/TextEditor.py
fltk/test/adjuster.py
fltk/test/arc.py
fltk/test/ask.py
fltk/test/bitmap.py
fltk/test/boxtype.py
fltk/test/browser.py
fltk/test/browserData.py
fltk/test/browser_cols.py
fltk/test/button.py
fltk/test/buttons.py
fltk/test/chart.py
fltk/test/check_browser.py
fltk/test/child_bug.py
fltk/test/clock.py
fltk/test/color_chooser.py
fltk/test/counters.py
fltk/test/cube.py
fltk/test/cursor.py
fltk/test/delwin.py
fltk/test/demos.py
fltk/test/device.py
fltk/test/dials.py
fltk/test/doublebuffer.py
fltk/test/draw.py
fltk/test/editor.py
fltk/test/exceptions.py
fltk/test/file_browser.py
fltk/test/file_chooser.py
fltk/test/fltk_threads.py
fltk/test/formsbitmap.py
fltk/test/glimage.py
fltk/test/grid_buttons.py
fltk/test/group.py
fltk/test/handle_events.py
fltk/test/hello.py
fltk/test/hello_utf8.py
fltk/test/help.py
fltk/test/help_dialog.py
fltk/test/iconize.py
fltk/test/idle.py
fltk/test/image.py
fltk/test/image_array.py
fltk/test/jpeg_buffer_test.py
fltk/test/listSelect.py
fltk/test/logo.py
fltk/test/logo1.gif
fltk/test/logo_gleam.py
fltk/test/menu.py
fltk/test/menu_label.py
fltk/test/menubar.py
fltk/test/message.py
fltk/test/message_de.py
fltk/test/multi.py
fltk/test/native-filechooser.py
fltk/test/pack.py
fltk/test/pixmap.py
fltk/test/postioner.py
fltk/test/preferences.py
fltk/test/radio.py
fltk/test/shapeGL.py
fltk/test/simple_table.py
fltk/test/simple_terminal.py
fltk/test/sliders.py
fltk/test/subwindow.py
fltk/test/sudoku.py
fltk/test/symbols.py
fltk/test/sys_exit_test.py
fltk/test/table.py
fltk/test/tabs.py
fltk/test/tile.py
fltk/test/timeout.py
fltk/test/timeout_bug.py
fltk/test/tree.py
fltk/test/tree_demo.py
fltk/test/tty.py
fltk/test/unittests.py
fltk/test/utf8.py
fltk/test/valuators.py
fltk/test/widget_properties.py
fltk/test/widgets.py
pyFltk1.4-1.4.1.0.dist-info/COPYING
pyFltk1.4-1.4.1.0.dist-info/METADATA
pyFltk1.4-1.4.1.0.dist-info/WHEEL
pyFltk1.4-1.4.1.0.dist-info/top_level.txt
pyFltk1.4-1.4.1.0.dist-info/RECORD
