Metadata-Version: 2.1
Name: pyFltk1.4
Version: 1.4.1.0
Summary: This is a Python wrapper for the FLTK
Home-page: http://pyfltk.sourceforge.net
Author: Andreas Held
Author-email: andreasheld@users.sourceforge.net
Project-URL: Bug Tracker, https://sourceforge.net/p/pyfltk/bugs/
Project-URL: Documentation, https://fltk.gitlab.io/fltk/
Project-URL: Source Code, https://sourceforge.net/p/pyfltk/code/HEAD/tree/branches/fltk1.4/
Keywords: python fltk
Classifier: License :: OSI Approved :: GNU Lesser General Public License v2 (LGPLv2)
License-File: COPYING
